uglylogger/__init__.py
uglylogger/logbase.py
uglylogger/logger.py
uglylogger/py.typed
uglylogger-0.8.1.dist-info/LICENSE
uglylogger-0.8.1.dist-info/METADATA
uglylogger-0.8.1.dist-info/WHEEL
uglylogger-0.8.1.dist-info/top_level.txt
uglylogger-0.8.1.dist-info/RECORD
