Metadata-Version: 2.1
Name: uglylogger
Version: 0.8.1
Summary: An ugly, slow Logger class for python
Author-email: Sevket Sureyya Caba <sevketcaba@gmail.com>
Maintainer-email: Sevket Sureyya Caba <sevketcaba@gmail.com>
License: MIT License
Project-URL: Homepage, https://github.com/sevketcaba/uglylogger
Project-URL: Bug Reports, https://github.com/sevketcaba/uglylogger/issues
Project-URL: Source, https://github.com/sevketcaba/uglylogger/
Keywords: python,python3,log,logger,oop,pretty,ugly
Classifier: Development Status :: 3 - Alpha
Classifier: Intended Audience :: Developers
Classifier: Topic :: Software Development :: Libraries
Classifier: License :: OSI Approved :: MIT License
Classifier: Programming Language :: Python :: 3
Classifier: Programming Language :: Python :: 3.10
Classifier: Programming Language :: Python :: 3.11
Classifier: Programming Language :: Python :: 3.12
Classifier: Programming Language :: Python :: 3 :: Only
Requires-Python: >=3.10
License-File: LICENSE
